picsellia_cv_engine/__init__.py
picsellia_cv_engine/enums.py
picsellia_cv_engine/logger.py
picsellia_cv_engine/core/__init__.py
picsellia_cv_engine/core/step_metadata.py
picsellia_cv_engine/core/contexts/__init__.py
picsellia_cv_engine/core/contexts/common/__init__.py
picsellia_cv_engine/core/contexts/common/picsellia_context.py
picsellia_cv_engine/core/contexts/processing/__init__.py
picsellia_cv_engine/core/contexts/processing/datalake/__init__.py
picsellia_cv_engine/core/contexts/processing/datalake/local_context.py
picsellia_cv_engine/core/contexts/processing/datalake/picsellia_context.py
picsellia_cv_engine/core/contexts/processing/dataset/__init__.py
picsellia_cv_engine/core/contexts/processing/dataset/local_context.py
picsellia_cv_engine/core/contexts/processing/dataset/picsellia_context.py
picsellia_cv_engine/core/contexts/processing/model/__init__.py
picsellia_cv_engine/core/contexts/processing/model/local_context.py
picsellia_cv_engine/core/contexts/processing/model/picsellia_context.py
picsellia_cv_engine/core/contexts/training/__init__.py
picsellia_cv_engine/core/contexts/training/local_context.py
picsellia_cv_engine/core/contexts/training/picsellia_context.py
picsellia_cv_engine/core/data/__init__.py
picsellia_cv_engine/core/data/coco_file_manager.py
picsellia_cv_engine/core/data/datalake/__init__.py
picsellia_cv_engine/core/data/datalake/datalake.py
picsellia_cv_engine/core/data/datalake/datalake_collection.py
picsellia_cv_engine/core/data/dataset/__init__.py
picsellia_cv_engine/core/data/dataset/base_dataset.py
picsellia_cv_engine/core/data/dataset/coco_dataset.py
picsellia_cv_engine/core/data/dataset/dataset_collection.py
picsellia_cv_engine/core/data/dataset/utils.py
picsellia_cv_engine/core/data/dataset/yolo_dataset.py
picsellia_cv_engine/core/logging/__init__.py
picsellia_cv_engine/core/logging/colors.py
picsellia_cv_engine/core/logging/stream_to_logger.py
picsellia_cv_engine/core/models/__init__.py
picsellia_cv_engine/core/models/model.py
picsellia_cv_engine-0.5.1.dist-info/METADATA
picsellia_cv_engine-0.5.1.dist-info/WHEEL
picsellia_cv_engine-0.5.1.dist-info/RECORD
