Metadata-Version: 2.4
Name: picsellia-cv-engine
Version: 0.5.1
Author-email: SoniaGrh <sonia.garrouch@hotmail.fr>
Requires-Python: <3.14,>=3.10
Requires-Dist: numpy<2.0.0,>=1.21
Requires-Dist: pandas<3.0.0,>=1.3
Requires-Dist: picsellia<7.0.0,>=6.29.0
Requires-Dist: pycocotools<3.0.0,>=2.0.4
Requires-Dist: scikit-learn<1.7,>=1.1
Requires-Dist: tabulate<0.10,>=0.8
Requires-Dist: toml<0.11.0,>=0.10.2
Provides-Extra: clip
Requires-Dist: accelerate==1.9.0; extra == 'clip'
Requires-Dist: datasets==4.0.0; extra == 'clip'
Requires-Dist: hdbscan==0.8.40; extra == 'clip'
Requires-Dist: matplotlib==3.10.5; extra == 'clip'
Requires-Dist: opencv-python==4.11.0.86; extra == 'clip'
Requires-Dist: protobuf==6.31.1; extra == 'clip'
Requires-Dist: torch==2.7.1; extra == 'clip'
Requires-Dist: torchvision==0.22.1; extra == 'clip'
Requires-Dist: transformers==4.54.1; extra == 'clip'
Requires-Dist: umap-learn==0.5.9.post2; extra == 'clip'
Provides-Extra: sam2
Requires-Dist: fvcore==0.1.5.post20221221; extra == 'sam2'
Requires-Dist: hydra-core>=1.3.2; extra == 'sam2'
Requires-Dist: iopath>=0.1.10; extra == 'sam2'
Requires-Dist: opencv-python==4.11.0.86; extra == 'sam2'
Requires-Dist: picsellia-sam2==0.1.0; extra == 'sam2'
Requires-Dist: submitit==1.5.3; extra == 'sam2'
Requires-Dist: tensorboard==2.20.0; extra == 'sam2'
Requires-Dist: tensordict==0.6.0; extra == 'sam2'
Requires-Dist: torchvision>=0.20.1; extra == 'sam2'
Requires-Dist: tqdm>=4.66.1; extra == 'sam2'
Provides-Extra: ultralytics
Requires-Dist: torch==2.7.1; extra == 'ultralytics'
Requires-Dist: ultralytics<9.0,>=8.0; extra == 'ultralytics'
